<Properties StartupConfiguration="{8AB8D515-058B-454E-89BA-0D6E7E142340}|http">
  <MonoDevelop.Ide.DebuggingService.PinnedWatches />
  <MonoDevelop.Ide.DebuggingService.Breakpoints>
    <BreakpointStore>
      <Breakpoint file="/Users/hoangdoan/Library/Mobile Documents/com~apple~CloudDocs/EDU/BaiTapLapTrinhWeb_ASP.Net MVC Core/SourceCode/ASP.Net_MVC_Core/Controllers/StudentController.cs" relfile="Controllers/StudentController.cs" line="63" column="1" />
    </BreakpointStore>
  </MonoDevelop.Ide.DebuggingService.Breakpoints>
  <MonoDevelop.Ide.Workspace ActiveConfiguration="Debug" />
  <MonoDevelop.Ide.Workbench ActiveDocument="Views/Account/Login.cshtml">
    <Files>
      <File FileName="Startup.cs" Line="84" Column="16" IsPinned="True" />
      <File FileName="Middleware/SystemAuthent.cs" />
      <File FileName="Controllers/StudentController.cs" Line="65" Column="27" />
      <File FileName="Controllers/AccountController.cs" Line="38" Column="35" />
      <File FileName="Models/AccountHelper.cs" />
      <File FileName="Views/Student/Index.cshtml" Line="18" Column="38" />
      <File FileName="Views/Student/Create.cshtml" Line="4" Column="14" />
      <File FileName="Views/Account/Login.cshtml" Line="10" Column="15" />
    </Files>
    <Pads>
      <Pad Id="ProjectPad">
        <State name="__root__">
          <Node name="ASP.Net_MVC_Core">
            <Node name="ASP.Net_MVC_Core">
              <Node name="Views">
                <Node name="Account" expanded="True">
                  <Node name="Login.cshtml" selected="True" />
                </Node>
              </Node>
            </Node>
          </Node>
        </State>
      </Pad>
      <Pad Id="MonoDevelop.Debugger.WatchPad">
        <State>
          <Value>user</Value>
          <Value>user</Value>
          <Value>userName</Value>
          <Value>userPass</Value>
          <Value>httpContext</Value>
        </State>
      </Pad>
    </Pads>
  </MonoDevelop.Ide.Workbench>
  <MultiItemStartupConfigurations />
  <MonoDevelop.Ide.ItemProperties.ASP.Net__MVC__Core PreferredExecutionTarget="/Applications/Google Chrome.app" />
</Properties>